SNPTMT/__init__.py
SNPTMT/snptmt.py
SNPTMT-0.0.11.dist-info/LICENSE
SNPTMT-0.0.11.dist-info/METADATA
SNPTMT-0.0.11.dist-info/WHEEL
SNPTMT-0.0.11.dist-info/top_level.txt
SNPTMT-0.0.11.dist-info/RECORD
