Metadata-Version: 2.1
Name: SNPTMT
Version: 0.0.11
Summary: Python module for searching for a new popular topics in the message threade
Home-page: https://github.com/FIvER4IK/snptmt
Download-URL: 
Author: FIvER4IK
Author-email: andrewshatalov3@gmail.com
Keywords: clusters clustering short text search new popular topics message thread
Classifier: Programming Language :: Python
Classifier: License :: OSI Approved :: MIT License
Classifier: Operating System :: OS Independent
Requires-Python: >=3.4
License-File: LICENSE
